pandas_sql_wrapper/__init__.py
pandas_sql_wrapper/wrapper.py
pandas_sql_wrapper-0.2.0.dist-info/DESCRIPTION.rst
pandas_sql_wrapper-0.2.0.dist-info/METADATA
pandas_sql_wrapper-0.2.0.dist-info/RECORD
pandas_sql_wrapper-0.2.0.dist-info/WHEEL
pandas_sql_wrapper-0.2.0.dist-info/metadata.json
pandas_sql_wrapper-0.2.0.dist-info/top_level.txt
