Metadata-Version: 2.0
Name: pandas-sql-wrapper
Version: 0.2.0
Summary: Tool to help pandas talk to mysql or postgresql databases.Introduces upsert and schema updating capabilities when writing dataframes to sql tables.
Home-page: https://github.com/Ianphorsman/PandasSqlWrapper
Author: Ian Horsman
Author-email: ianphorsman@gmail.com
License: MIT
Platform: UNKNOWN
Requires-Dist: numpy
Requires-Dist: pandas
Requires-Dist: pymysql
Requires-Dist: sqlalchemy
Requires-Dist: pg8000
